apiverve_texttocolor/__init__.py
apiverve_texttocolor/apiClient.py
apiverve_texttocolor/exceptions.py
apiverve_texttocolor/setup.py
apiverve_texttocolor/setup_dep.py
apiverve_texttocolor/tests/__init__.py
apiverve_texttocolor/tests/test_api.py
apiverve_texttocolor-1.1.5.dist-info/LICENSE
apiverve_texttocolor-1.1.5.dist-info/METADATA
apiverve_texttocolor-1.1.5.dist-info/WHEEL
apiverve_texttocolor-1.1.5.dist-info/top_level.txt
apiverve_texttocolor-1.1.5.dist-info/RECORD
